GMXMMPBSA/API.py
GMXMMPBSA/GMXMMPBSA.sh
GMXMMPBSA/__init__.py
GMXMMPBSA/_version.py
GMXMMPBSA/alamdcrd.py
GMXMMPBSA/amber_outputs.py
GMXMMPBSA/app.py
GMXMMPBSA/calculation.py
GMXMMPBSA/commandlineparser.py
GMXMMPBSA/createinput.py
GMXMMPBSA/exceptions.py
GMXMMPBSA/fake_mpi.py
GMXMMPBSA/infofile.py
GMXMMPBSA/input_parser.py
GMXMMPBSA/main.py
GMXMMPBSA/make_top.py
GMXMMPBSA/make_trajs.py
GMXMMPBSA/output_file.py
GMXMMPBSA/parm_setup.py
GMXMMPBSA/tester.py
GMXMMPBSA/timer.py
GMXMMPBSA/utils.py
GMXMMPBSA/analyzer/__init__.py
GMXMMPBSA/analyzer/chartsettings.py
GMXMMPBSA/analyzer/customitem.py
GMXMMPBSA/analyzer/dialogs.py
GMXMMPBSA/analyzer/gui.py
GMXMMPBSA/analyzer/items_delegate.py
GMXMMPBSA/analyzer/plots.py
GMXMMPBSA/analyzer/utils.py
GMXMMPBSA/analyzer/parametertree/Parameter.py
GMXMMPBSA/analyzer/parametertree/ParameterItem.py
GMXMMPBSA/analyzer/parametertree/ParameterTree.py
GMXMMPBSA/analyzer/parametertree/__init__.py
GMXMMPBSA/analyzer/parametertree/parameterTypes.py
GMXMMPBSA/analyzer/style/Accent.png
GMXMMPBSA/analyzer/style/ArmyRose_5.png
GMXMMPBSA/analyzer/style/ArmyRose_7.png
GMXMMPBSA/analyzer/style/Balance_5.png
GMXMMPBSA/analyzer/style/Balance_7.png
GMXMMPBSA/analyzer/style/BrBG_5.png
GMXMMPBSA/analyzer/style/BrBG_7.png
GMXMMPBSA/analyzer/style/Curl_5.png
GMXMMPBSA/analyzer/style/Curl_7.png
GMXMMPBSA/analyzer/style/Dark2.png
GMXMMPBSA/analyzer/style/Delta_5.png
GMXMMPBSA/analyzer/style/Delta_7.png
GMXMMPBSA/analyzer/style/Geyser_5.png
GMXMMPBSA/analyzer/style/Geyser_7.png
GMXMMPBSA/analyzer/style/PRGn_5.png
GMXMMPBSA/analyzer/style/PRGn_7.png
GMXMMPBSA/analyzer/style/Paired.png
GMXMMPBSA/analyzer/style/Pastel1.png
GMXMMPBSA/analyzer/style/Pastel2.png
GMXMMPBSA/analyzer/style/PiYG_5.png
GMXMMPBSA/analyzer/style/PiYG_7.png
GMXMMPBSA/analyzer/style/PuOr_5.png
GMXMMPBSA/analyzer/style/PuOr_7.png
GMXMMPBSA/analyzer/style/RdBu_5.png
GMXMMPBSA/analyzer/style/RdBu_7.png
GMXMMPBSA/analyzer/style/RdGy_5.png
GMXMMPBSA/analyzer/style/RdGy_7.png
gmx_MMPBSA-1.6.4.dist-info/LICENSE.txt
gmx_MMPBSA-1.6.4.dist-info/METADATA
gmx_MMPBSA-1.6.4.dist-info/WHEEL
gmx_MMPBSA-1.6.4.dist-info/entry_points.txt
gmx_MMPBSA-1.6.4.dist-info/top_level.txt
gmx_MMPBSA-1.6.4.dist-info/RECORD
