Metadata-Version: 2.1
Name: gmx_MMPBSA
Version: 1.6.4
Summary: gmx_MMPBSA is a new tool based on AMBER's MMPBSA.py aiming to perform end-state free energy  calculations with GROMACS files
Home-page: https://github.com/Valdes-Tresanco-MS/gmx_MMPBSA
Author: Mario S. Valdes-Tresanco and Mario E. Valdes-Tresanco 
Author-email: mariosergiovaldes145@gmail.com
Maintainer: Mario S. Valdes-Tresanco
Maintainer-email: mariosergiovaldes145@gmail.com
License: GPLv3
Keywords: gmx_MMPBSA,MMPBSA,MMGBSA,GROMACS,AmberTools
License-File: LICENSE.txt
Requires-Dist: numpy==1.26.4
Requires-Dist: pandas==1.5.3
Requires-Dist: matplotlib==3.7.3
Requires-Dist: seaborn==0.11.2
Requires-Dist: scipy==1.14.1
Requires-Dist: mpi4py==4.0.1
Requires-Dist: parmed>=4.2.2
Requires-Dist: tqdm
